cascade_filter/__init__.py
cascade_filter/clause.py
cascade_filter/exception.py
cascade_filter/field_type.py
cascade_filter/compliance_checker/__init__.py
cascade_filter/compliance_checker/array.py
cascade_filter/compliance_checker/base.py
cascade_filter/compliance_checker/boolean.py
cascade_filter/compliance_checker/checker.py
cascade_filter/compliance_checker/choice.py
cascade_filter/compliance_checker/date.py
cascade_filter/compliance_checker/decorator.py
cascade_filter/compliance_checker/multi.py
cascade_filter/compliance_checker/numeric.py
cascade_filter/compliance_checker/single.py
cascade_filter/compliance_checker/text.py
cascade_filter/compliance_checker/uuid.py
cascade_filter/django/__init__.py
cascade_filter/django/field.py
cascade_filter/django/validator.py
cascade_filter/django/widget.py
cascade_filter/django/filter/__init__.py
cascade_filter/django/filter/array_filter_mixin.py
cascade_filter/django/filter/boolean_filter_mixin.py
cascade_filter/django/filter/choice_filter_mixin.py
cascade_filter/django/filter/date_filter_mixin.py
cascade_filter/django/filter/filter.py
cascade_filter/django/filter/multi_filter_mixin.py
cascade_filter/django/filter/numeric_filter_mixin.py
cascade_filter/django/filter/single_filter_mixin.py
cascade_filter/django/filter/text_filter_mixin.py
cascade_filter/django/filter/uuid_filter_mixin.py
cascade_filter/filter/__init__.py
cascade_filter/filter/deserialization.py
cascade_filter/filter/type.py
cascade_filter/filter/array/__init__.py
cascade_filter/filter/array/dataclass.py
cascade_filter/filter/array/deserializer.py
cascade_filter/filter/array/validator.py
cascade_filter/filter/base/__init__.py
cascade_filter/filter/base/dataclass.py
cascade_filter/filter/base/validator.py
cascade_filter/filter/boolean/__init__.py
cascade_filter/filter/boolean/dataclass.py
cascade_filter/filter/boolean/deserializer.py
cascade_filter/filter/boolean/validator.py
cascade_filter/filter/choice/__init__.py
cascade_filter/filter/choice/dataclass.py
django_cascade_filter-0.1.0rc7.dist-info/METADATA
django_cascade_filter-0.1.0rc7.dist-info/WHEEL
django_cascade_filter-0.1.0rc7.dist-info/RECORD
