Metadata-Version: 2.4
Name: django-cascade-filter
Version: 0.1.0rc7
Summary: Cascade filters in the Django Admin Panel
Requires-Python: >=3.9
Requires-Dist: arrow>=1.3.0
Requires-Dist: django>=3
